brim_cloud_client/BRIM.py
brim_cloud_client/__init__.py
brim_cloud_client/loader.py
brim_cloud_client/test.py
brim_cloud_client-1.0.3.dist-info/LICENSE
brim_cloud_client-1.0.3.dist-info/METADATA
brim_cloud_client-1.0.3.dist-info/WHEEL
brim_cloud_client-1.0.3.dist-info/top_level.txt
brim_cloud_client-1.0.3.dist-info/RECORD
