Metadata-Version: 2.1
Name: brim-cloud-client
Version: 1.0.3
Summary: BRIM cloud client
Author-email: Lance1o7 <10292888+Lance1o7@users.noreply.github.com>
Project-URL: Homepage, https://github.com/Lance1o7/brim-cloud-client
Project-URL: Bug Tracker, https://github.com/Lance1o7/brim-cloud-client/issues
Classifier: Programming Language :: Python :: 3
Classifier: License :: OSI Approved :: GNU General Public License v2 (GPLv2)
Classifier: Operating System :: OS Independent
Requires-Python: >=3.7
License-File: LICENSE
